anki_niobium/__init__.py
anki_niobium/cli.py
anki_niobium/io.py
anki_niobium-0.2.3.dist-info/METADATA
anki_niobium-0.2.3.dist-info/WHEEL
anki_niobium-0.2.3.dist-info/entry_points.txt
anki_niobium-0.2.3.dist-info/licenses/LICENSE
anki_niobium-0.2.3.dist-info/RECORD
