Metadata-Version: 2.4
Name: anki-niobium
Version: 0.2.3
Summary: NIOBIUM: Nadia's Image Occlusion Booster Is UnManned - A CLI tool for extracting text and image-occlusion-style notes from images and PDFs for Anki
Project-URL: Homepage, https://github.com/agahkarakuzu/niobium
Project-URL: Repository, https://github.com/agahkarakuzu/niobium
Project-URL: Issues, https://github.com/agahkarakuzu/niobium/issues
Author-email: Agah Karakuzu <agahkarakuzu@gmail.com>
License: GPL-3.0
License-File: LICENSE
Keywords: anki,education,flashcards,image-occlusion,ocr,pdf
Classifier: Development Status :: 4 - Beta
Classifier: Intended Audience :: Education
Classifier: License :: OSI Approved :: GNU General Public License v3 (GPLv3)
Classifier: Programming Language :: Python :: 3
Classifier: Programming Language :: Python :: 3.8
Classifier: Programming Language :: Python :: 3.9
Classifier: Programming Language :: Python :: 3.10
Classifier: Programming Language :: Python :: 3.11
Classifier: Programming Language :: Python :: 3.12
Classifier: Topic :: Education
Classifier: Topic :: Scientific/Engineering :: Image Recognition
Requires-Python: >=3.8
Requires-Dist: click
Requires-Dist: easyocr
Requires-Dist: numpy<2.0
Requires-Dist: pillow
Requires-Dist: pymupdf
Requires-Dist: requests
Requires-Dist: tqdm
